.gitignore
CHANGELOG.rst
CONTRIBUTING.rst
LICENSE.txt
README.rst
nbval_sanitize.cfg
pytest.ini
ruff.toml
setup.py
test_requirements.txt
.github/workflows/test.yaml
docs/.gitignore
docs/.nojekyll
docs/Makefile
docs/RBD_average.nblink
docs/README.rst
docs/acknowledgments.rst
docs/biophysical_model.nblink
docs/concentration_set.nblink
docs/conf.py
docs/doc_requirements.txt
docs/expt_design.rst
docs/fit_2epitope.nblink
docs/fit_RBD.nblink
docs/index.rst
docs/installation.rst
docs/library_size.nblink
docs/mutation_rate.nblink
docs/optimization.nblink
docs/package_index.rst
docs/partition_function.nblink
docs/real_LyCoV1404.nblink
docs/real_cocktail.nblink
docs/reference_site_numbering.nblink
docs/regularization.rst
docs/simulate_RBD.nblink
docs/specify_epitopes.nblink
docs/visualize_RBD.nblink
docs/_static/BloomLogo.jpg
notebooks/2epitope_escape.csv
notebooks/2epitope_model_curve_specs.csv
notebooks/6M0J.pdb
notebooks/BA.1_site_numbering_map.csv
notebooks/Env_site_numbering_map.csv
notebooks/Env_trimer.pdb
notebooks/Lib-2_2022-06-22_thaw-1_LyCoV-1404_1_prob_escape.csv
notebooks/Omicron_BA.1_muteffects_observed.csv
notebooks/RBD_activity_wt_df.csv
notebooks/RBD_average.ipynb
notebooks/RBD_bootstrap.ipynb
notebooks/RBD_mean_class_1.pdb
notebooks/RBD_mean_class_1.png
notebooks/RBD_mean_class_2.pdb
notebooks/RBD_mean_class_2.png
notebooks/RBD_mean_class_3.pdb
notebooks/RBD_mean_class_3.png
notebooks/RBD_mut_escape_df.csv
notebooks/RBD_mut_escape_df.py
notebooks/RBD_mutation_escape_fractions.csv
notebooks/RBD_seq.fasta
notebooks/RBD_variants_escape_exact.csv
notebooks/RBD_variants_escape_noisy.csv
notebooks/README.md
notebooks/biophysical_model.ipynb
notebooks/concentration_set.ipynb
notebooks/fit_2epitope.ipynb
notebooks/fit_RBD.ipynb
notebooks/libA_220810_1_1C04-5G04_1_prob_escape.csv
notebooks/library_size.ipynb
notebooks/mutation_rate.ipynb
notebooks/optimization.ipynb
notebooks/partition_function.ipynb
notebooks/real_LyCoV1404.ipynb
notebooks/real_cocktail.ipynb
polyclonal.egg-info/PKG-INFO
polyclonal.egg-info/SOURCES.txt
polyclonal.egg-info/dependency_links.txt
polyclonal.egg-info/requires.txt
polyclonal.egg-info/top_level.txt
