Metadata-Version: 2.4
Name: polyclonal
Version: 6.17
Summary: Model mutational escape from polyclonal antibodies.
Home-page: https://github.com/jbloomlab/polyclonal
Download-URL: https://github.com/jbloomlab/polyclonal/tarball/6.17
Author: `the Bloom lab <https://jbloomlab.org>`_
Author-email: jbloom@fredhutch.org
License: GPLv3
Platform: Linux and Mac OS X.
License-File: LICENSE.txt
Requires-Dist: altair>=5.0.0
Requires-Dist: binarymap>=0.8
Requires-Dist: biopython>=1.79
Requires-Dist: frozendict>=2.0.7
Requires-Dist: matplotlib>=3.1
Requires-Dist: natsort>=8.0
Requires-Dist: numpy>=1.17
Requires-Dist: pandas>=1.5
Requires-Dist: pyarrow
Requires-Dist: requests
Requires-Dist: scipy>=1.7.1
Dynamic: author
Dynamic: author-email
Dynamic: description
Dynamic: download-url
Dynamic: home-page
Dynamic: license
Dynamic: license-file
Dynamic: platform
Dynamic: requires-dist
Dynamic: summary
